pfinance/__init__.py
pfinance/conversion.py
pfinance/depreciation.py
pfinance/general.py
pfinance/securities.py
pfinance/time_value.py
tests/__init__.py
tests/test_functions.py
pfinance-0.2.2.dist-info/LICENSE
pfinance-0.2.2.dist-info/METADATA
pfinance-0.2.2.dist-info/WHEEL
pfinance-0.2.2.dist-info/top_level.txt
pfinance-0.2.2.dist-info/RECORD
