Metadata-Version: 2.1
Name: pfinance
Version: 0.2.2
Summary: Financial mathematics library
Home-page: https://github.com/j-pettit/pfinance/
Author: Julian Pettit, Fernando Yee
Author-email: julian.s.pettit@gmail.com, fernando.yee97@gmail.com
License: MIT
Project-URL: Source, https://github.com/j-pettit/pfinance/
Project-URL: Tracker, https://github.com/j-pettit/pfinance/issues
Keywords: finance,mathematics
Platform: UNKNOWN
Requires-Python: >=3.9
License-File: LICENSE
Provides-Extra: dev
Requires-Dist: nox ; extra == 'dev'
